argus/__init__.py
argus/loss.py
argus/optimizer.py
argus/types.py
argus/utils.py
argus/callbacks/__init__.py
argus/callbacks/callback.py
argus/callbacks/checkpoints.py
argus/callbacks/early_stopping.py
argus/callbacks/logging.py
argus/callbacks/lr_schedulers.py
argus/engine/__init__.py
argus/engine/engine.py
argus/metrics/__init__.py
argus/metrics/categorical_accuracy.py
argus/metrics/loss.py
argus/metrics/metric.py
argus/model/__init__.py
argus/model/build.py
argus/model/load.py
argus/model/model.py
pytorch_argus-1.1.0.dist-info/LICENSE
pytorch_argus-1.1.0.dist-info/METADATA
pytorch_argus-1.1.0.dist-info/WHEEL
pytorch_argus-1.1.0.dist-info/top_level.txt
pytorch_argus-1.1.0.dist-info/RECORD
