Metadata-Version: 2.1
Name: pytorch-argus
Version: 1.1.0
Summary: Argus is a lightweight library for training neural networks in PyTorch.
Author-email: Ruslan Baikulov <ruslan1123@gmail.com>
License: MIT License
Project-URL: Repository, https://github.com/lRomul/argus
Project-URL: Documentation, https://pytorch-argus.readthedocs.io/
Classifier: Development Status :: 5 - Production/Stable
Classifier: License :: OSI Approved :: MIT License
Classifier: Intended Audience :: Developers
Classifier: Intended Audience :: Science/Research
Classifier: Operating System :: OS Independent
Classifier: Programming Language :: Python :: 3
Classifier: Programming Language :: Python :: 3.8
Classifier: Programming Language :: Python :: 3.9
Classifier: Programming Language :: Python :: 3.10
Classifier: Programming Language :: Python :: 3.11
Classifier: Topic :: Scientific/Engineering
Classifier: Topic :: Scientific/Engineering :: Artificial Intelligence
Classifier: Topic :: Software Development
Classifier: Topic :: Software Development :: Libraries
Classifier: Topic :: Software Development :: Libraries :: Python Modules
Requires-Python: >=3.8
License-File: LICENSE
Requires-Dist: torch >=2.0.0
Provides-Extra: docs
Requires-Dist: sphinx ==7.3.7 ; extra == 'docs'
Requires-Dist: pydata-sphinx-theme ==0.15.2 ; extra == 'docs'
Provides-Extra: examples
Requires-Dist: torchvision ==0.18.0 ; extra == 'examples'
Requires-Dist: notebook ==7.1.3 ; extra == 'examples'
Requires-Dist: timm ==0.9.16 ; extra == 'examples'
Provides-Extra: tests
Requires-Dist: pytest ==8.1.1 ; extra == 'tests'
Requires-Dist: pytest-cov ==5.0.0 ; extra == 'tests'
Requires-Dist: ruff ==0.4.1 ; extra == 'tests'
